mkdocs_apidoc/__init__.py
mkdocs_apidoc/config.py
mkdocs_apidoc/models.py
mkdocs_apidoc/parser.py
mkdocs_apidoc/plugin.py
mkdocs_apidoc/render.py
mkdocs_apidoc-0.2.3.dist-info/entry_points.txt
mkdocs_apidoc-0.2.3.dist-info/LICENSE.md
mkdocs_apidoc-0.2.3.dist-info/WHEEL
mkdocs_apidoc-0.2.3.dist-info/METADATA
mkdocs_apidoc-0.2.3.dist-info/RECORD
